aiwb/__init__.py
aiwb/cli.py
aiwb/logger.py
aiwb/session.py
aiwb/simply.py
aiwb/token.py
aiwb/utils.py
aiwb/cli/__init__.py
aiwb/cli/auth.py
aiwb/cli/cli.py
aiwb/cli/workbench.py
aiwb/core/__init__.py
aiwb/core/auth.py
aiwb/core/model.py
aiwb/core/session.py
aiwb/core/token.py
aiwb/core/workbench.py
aiwb/utils/__init__.py
aiwb/utils/utils.py
aiwb-0.0.1.data/scripts/aiwb
aiwb-0.0.1.dist-info/METADATA
aiwb-0.0.1.dist-info/WHEEL
aiwb-0.0.1.dist-info/top_level.txt
aiwb-0.0.1.dist-info/RECORD
